{
  "build": "hcfcfb64_0",
  "build_number": 0,
  "channel": "https://conda.anaconda.org/conda-forge/win-64",
  "constrains": [],
  "depends": [
    "ucrt >=10.0.20348.0",
    "vc >=14.2,<15",
    "vc14_runtime >=14.29.30139"
  ],
  "extracted_package_dir": "C:\\Users\\Sicario\\anaconda3\\pkgs\\libsqlite-3.45.3-hcfcfb64_0",
  "files": [
    "Library/bin/sqlite3.dll",
    "Library/include/sqlite3.h",
    "Library/include/sqlite3ext.h",
    "Library/lib/sqlite3.lib",
    ".nonadmin"
  ],
  "fn": "libsqlite-3.45.3-hcfcfb64_0.conda",
  "license": "Unlicense",
  "link": {
    "source": "C:\\Users\\Sicario\\anaconda3\\pkgs\\libsqlite-3.45.3-hcfcfb64_0",
    "type": 1
  },
  "md5": "73f5dc8e2d55d9a1e14b11f49c3b4a28",
  "name": "libsqlite",
  "package_tarball_full_path": "C:\\Users\\Sicario\\anaconda3\\pkgs\\libsqlite-3.45.3-hcfcfb64_0.conda",
  "paths_data": {
    "paths": [],
    "paths_version": 1
  },
  "requested_spec": "None",
  "sha256": "06ec75faa51d7ec6d5db98889e869b579a9df19d7d3d9baff8359627da4a3b7e",
  "size": 870518,
  "subdir": "win-64",
  "timestamp": 1713367888000,
  "url": "https://conda.anaconda.org/conda-forge/win-64/libsqlite-3.45.3-hcfcfb64_0.conda",
  "version": "3.45.3"
}